<?xml version="1.0"?>
<ldap>
    <users basedn="ou=users,dc=marklogic,dc=local">
        <user dn="cn=manager">
            <sAMAccountName>manager</sAMAccountName>
            <userPassword>password</userPassword>
        </user>
        <user dn="cn=admin">
            <sAMAccountName>admin</sAMAccountName>
            <memberOf>cn=admin,ou=groups,dc=marklogic,dc=local</memberOf>
            <userPassword>password</userPassword>
            <rfc6238code>IVKFK3B4OI4VQMDGENEVURT5GRYFIWTM</rfc6238code>
        </user>
        <user dn="cn=user1">
            <sAMAccountName>user1</sAMAccountName>
            <memberOf>cn=appreader,ou=groups,dc=marklogic,dc=local</memberOf>
            <memberOf>cn=appwriter,ou=groups,dc=marklogic,dc=local</memberOf>
            <memberOf>cn=appadmin,ou=groups,dc=marklogic,dc=local</memberOf>
            <userPassword>password</userPassword>
            <rfc6238code>IVKFK3B4OI4VQMDGENEVURT5GRYFIWTM</rfc6238code>
        </user>
        <user dn="cn=user2">
            <sAMAccountName>user2</sAMAccountName>
            <memberOf>cn=appreader,ou=groups,dc=marklogic,dc=local</memberOf>
            <memberOf>cn=appwriter,ou=groups,dc=marklogic,dc=local</memberOf>
            <userPassword>password</userPassword>
        </user>
        <user dn="cn=user3">
            <sAMAccountName>user3</sAMAccountName>
            <memberOf>cn=appreader,ou=groups,dc=marklogic,dc=local</memberOf>
            <userPassword>password</userPassword>
        </user>
        <user dn="cn=user4">
            <sAMAccountName>user4</sAMAccountName>
            <userPassword>password</userPassword>
        </user>
        <user dn="cn=testuser">
            <sAMAccountName>testuser</sAMAccountName>
            <userPassword>password</userPassword>
        </user>
    </users>
</ldap>